cdp_data/__init__.py
cdp_data/constants.py
cdp_data/datasets.py
cdp_data/instances.py
cdp_data/keywords.py
cdp_data/plots.py
cdp_data/py.typed
cdp_data/bin/__init__.py
cdp_data/bin/research/__init__.py
cdp_data/bin/research/cdp_councils_in_action_2022_content.py
cdp_data/tests/__init__.py
cdp_data/tests/conftest.py
cdp_data/tests/test_datasets.py
cdp_data/tests/test_keywords_and_plotting.py
cdp_data/tests/utils/__init__.py
cdp_data/tests/utils/test_incremental_average.py
cdp_data/utils/__init__.py
cdp_data/utils/db_utils.py
cdp_data/utils/fs_utils.py
cdp_data/utils/incremental_average.py
docs/conf.py
docs/contributing.rst
docs/index.rst
docs/installation.rst
docs/_static/header-keywords-over-time.png
docs/_static/seattle-keywords-over-time.png
notebooks/historical_vote_proportions.ipynb
notebooks/plot_keyword_history.ipynb
scripts/generate-readme-figs.py
cdp_data-0.0.10.dist-info/LICENSE
cdp_data-0.0.10.dist-info/METADATA
cdp_data-0.0.10.dist-info/WHEEL
cdp_data-0.0.10.dist-info/top_level.txt
cdp_data-0.0.10.dist-info/RECORD
