Metadata-Version: 2.1
Name: cdp-data
Version: 0.0.10
Summary: Data Utilities and Processing Generalized for All CDP Instances
Author-email: "Eva Maxfield Brown, Council Data Project Contributors" <evamaxfieldbrown@gmail.com>
License: MIT License
Project-URL: Homepage, https://github.com/CouncilDataProject/cdp-data
Project-URL: Bug Tracker, https://github.com/CouncilDataProject/cdp-data/issues
Project-URL: Documentation, https://CouncilDataProject.github.io/cdp-data
Project-URL: User Support, https://github.com/CouncilDataProject/cdp-data/issues
Classifier: Development Status :: 4 - Beta
Classifier: Natural Language :: English
Classifier: Programming Language :: Python :: 3.8
Classifier: Programming Language :: Python :: 3.9
Classifier: Programming Language :: Python :: 3.10
Requires-Python: >=3.8
License-File: LICENSE
Requires-Dist: cdp-backend (>=3.0.15)
Requires-Dist: nltk (~=3.6)
Requires-Dist: numpy (~=1.0)
Requires-Dist: pandas (~=1.0)
Requires-Dist: tqdm (>=4.63)
Requires-Dist: dataclasses-json
Requires-Dist: fireo
Requires-Dist: gcsfs
Provides-Extra: dev
Requires-Dist: ipython (>=8.4.0) ; extra == 'dev'
Requires-Dist: jupyterlab (>=3.2.8) ; extra == 'dev'
Provides-Extra: docs
Requires-Dist: m2r2 (>=0.2.7) ; extra == 'docs'
Requires-Dist: Sphinx (>=4.0.0) ; extra == 'docs'
Requires-Dist: furo (>=2022.4.7) ; extra == 'docs'
Requires-Dist: numpydoc ; extra == 'docs'
Requires-Dist: sphinx-copybutton ; extra == 'docs'
Requires-Dist: docutils (<0.19,>=0.18) ; extra == 'docs'
Provides-Extra: lint
Requires-Dist: black (>=22.3.0) ; extra == 'lint'
Requires-Dist: check-manifest (>=0.48) ; extra == 'lint'
Requires-Dist: ruff (>=0.0.216) ; extra == 'lint'
Requires-Dist: mypy (>=0.790) ; extra == 'lint'
Requires-Dist: pre-commit (>=2.20.0) ; extra == 'lint'
Provides-Extra: plot
Requires-Dist: matplotlib (>=3) ; extra == 'plot'
Requires-Dist: seaborn (>=0.11.2) ; extra == 'plot'
Requires-Dist: pyarrow (>=7.0.0) ; extra == 'plot'
Requires-Dist: ipywidgets (>=7.7.0) ; extra == 'plot'
Provides-Extra: test
Requires-Dist: coverage (>=5.1) ; extra == 'test'
Requires-Dist: pytest (>=5.4.3) ; extra == 'test'
Requires-Dist: pytest-cov (>=2.9.0) ; extra == 'test'
Requires-Dist: pytest-raises (>=0.11) ; extra == 'test'
Provides-Extra: transformers
Requires-Dist: sentence-transformers (~=2.2.2) ; extra == 'transformers'
